embeddings/__init__.py
embeddings/constants.py
embeddings/model.py
embeddings/tokenizer.py
tests/__init__.py
tests/conftest.py
tests/test_basic_tokenizer.py
tests/test_word2vec.py
screeve_embeddings-0.2.0.dist-info/LICENSE
screeve_embeddings-0.2.0.dist-info/METADATA
screeve_embeddings-0.2.0.dist-info/WHEEL
screeve_embeddings-0.2.0.dist-info/top_level.txt
screeve_embeddings-0.2.0.dist-info/RECORD
